{
	"@metadata": {
		"authors": [
			"P. S. F. Freitas"
		]
	},
	"Apps.subtitle": "peteĩ techa myatyrõ hekoha",
	"Apps.blocklyMessage": "Blockly",
	"Apps.codeTooltip": "Ehecha JavaScript mba'e apopyre.",
	"Apps.linkTooltip": "Oñongatu ha ombojoaju vorekuéra.",
	"Apps.runTooltip": "Pejapo pe jejaporã vorekuéra ohechauka akue tembiapo rendápe.",
	"Apps.runProgram": "Pejapo pe Jejaporã",
	"Apps.resetProgram": "Ñepyrũ jey",
	"Apps.catLogic": "Kuaarape",
	"Apps.catLoops": "Tapykuegua",
	"Apps.catMath": "Papapykuaa",
	"Apps.catText": "Jehaipy",
	"Apps.catLists": "Tysýi",
	"Apps.catColour": "Sa'y",
	"Apps.catVariables": "Ñemoambuéva",
	"Apps.catProcedures": "Aporeko",
	"Apps.httpRequestError": "Peteĩ tekojepe'y ohechauka.",
	"Apps.linkAlert": "Temboja'o nde vorekuéra ko joaju ndie:\n\n%1",
	"Apps.listVariable": "tysýi",
	"Apps.textVariable": "jehaipy",
	"Plane.placeholder": "?"
}
